paymentus_core/__init__.py
paymentus_core/client.py
paymentus_core/exceptions.py
paymentus_core/sdk.py
paymentus_core/version.py
paymentus_core-1.0.3.dist-info/METADATA
paymentus_core-1.0.3.dist-info/WHEEL
paymentus_core-1.0.3.dist-info/top_level.txt
paymentus_core-1.0.3.dist-info/RECORD
