Metadata-Version: 2.4
Name: paymentus-core
Version: 1.0.3
Summary: Paymentus Python Core SDK
Author-email: Paymentus SDK Support <sdksupport@paymentus.com>
Maintainer-email: Paymentus SDK Support <sdksupport@paymentus.com>
License-Expression: MIT
Project-URL: Homepage, https://www.paymentus.com/
Project-URL: Source, https://developer.paymentus.io/
Keywords: paymentus,core,client,sdk,api,http,rest
Requires-Python: >=3.9
Requires-Dist: requests>=2.31.0
Requires-Dist: urllib3>=2.0.0
Requires-Dist: pydantic>=2.0.0
Requires-Dist: python-dotenv>=1.0.0
Provides-Extra: dev
Requires-Dist: pytest>=7.0.0; extra == "dev"
Requires-Dist: black>=22.0.0; extra == "dev"
Requires-Dist: flake8>=4.0.0; extra == "dev"
Requires-Dist: isort>=5.0.0; extra == "dev"
Requires-Dist: twine>=4.0.0; extra == "dev"
Requires-Dist: build>=0.8.0; extra == "dev"
